aistudio_sdk/__init__.py
aistudio_sdk/cmdline.py
aistudio_sdk/config.py
aistudio_sdk/dot.py
aistudio_sdk/errors.py
aistudio_sdk/file_download.py
aistudio_sdk/hub.py
aistudio_sdk/log.py
aistudio_sdk/snapshot_download.py
aistudio_sdk/switch_downoad.py
aistudio_sdk/constant/__init__.py
aistudio_sdk/constant/const.py
aistudio_sdk/constant/err_code.py
aistudio_sdk/constant/version.py
aistudio_sdk/requests/__init__.py
aistudio_sdk/requests/dataset.py
aistudio_sdk/requests/hub.py
aistudio_sdk/requests/pipeline.py
aistudio_sdk/sdk/__init__.py
aistudio_sdk/sdk/pipeline.py
aistudio_sdk/tests/__init__.py
aistudio_sdk/utils/__init__.py
aistudio_sdk/utils/bos_sdk.py
aistudio_sdk/utils/caching.py
aistudio_sdk/utils/util.py
aistudio_sdk-0.3.4.dist-info/METADATA
aistudio_sdk-0.3.4.dist-info/WHEEL
aistudio_sdk-0.3.4.dist-info/entry_points.txt
aistudio_sdk-0.3.4.dist-info/top_level.txt
aistudio_sdk-0.3.4.dist-info/RECORD
