Metadata-Version: 2.1
Name: aistudio-sdk
Version: 0.3.4
Summary: Python client library for the AIStudio API
Home-page: UNKNOWN
License: UNKNOWN
Platform: UNKNOWN
Classifier: Programming Language :: Python
Requires-Dist: requests
Requires-Dist: tqdm
Requires-Dist: bce-python-sdk
Requires-Dist: prettytable
Requires-Dist: click
